servra.py
servra-0.0.0.dist-info/LICENSE
servra-0.0.0.dist-info/METADATA
servra-0.0.0.dist-info/WHEEL
servra-0.0.0.dist-info/top_level.txt
servra-0.0.0.dist-info/RECORD
